covid_bks_ba/__init__.py
covid_bks_ba/config/__init__.py
covid_bks_ba/config/__main__.py
covid_bks_ba/config/default.py
covid_bks_ba/config/tmp_conf.py
covid_bks_ba/dataset_processing/__init__.py
covid_bks_ba/dataset_processing/fetch/__init__.py
covid_bks_ba/dataset_processing/fetch/__main__.py
covid_bks_ba/hyper_parameter_tuning/__init__.py
covid_bks_ba/hyper_parameter_tuning/bks/__init__.py
covid_bks_ba/hyper_parameter_tuning/bks/__main__.py
covid_bks_ba/hyper_parameter_tuning/bks/metric.py
covid_bks_ba/hyper_parameter_tuning/result/__init__.py
covid_bks_ba/models/__init__.py
covid_bks_ba/models/bks.py
covid_bks_ba/result/__init__.py
covid_bks_ba/seed/__init__.py
covid_bks_ba/stack/__init__.py
covid_bks_ba/stack/__main__.py
covid_bks_ba-0.0.1.dist-info/METADATA
covid_bks_ba-0.0.1.dist-info/WHEEL
covid_bks_ba-0.0.1.dist-info/RECORD
